puloon/__init__.py
puloon/__main__.py
puloon/cli.py
puloon/lcdm2000.py
puloon/lcdm4000.py
puloon/lcdm_test.py
puloon-0.2.3.dist-info/LICENSE
puloon-0.2.3.dist-info/METADATA
puloon-0.2.3.dist-info/WHEEL
puloon-0.2.3.dist-info/entry_points.txt
puloon-0.2.3.dist-info/RECORD
