Metadata-Version: 2.1
Name: puloon
Version: 0.2.3
Summary: Puloon LCDM-4000 communication protocol python implementation
Home-page: https://gitlab.com/aiba.kg93/puloon-py
Keywords: puloon,lcdm,lcdm-4000
Author: Aibek
Author-email: aiba.kg93@gmail.com
Requires-Python: >=3.9,<4.0
Classifier: Programming Language :: Python :: 3
Classifier: Programming Language :: Python :: 3.9
Classifier: Programming Language :: Python :: 3.10
Classifier: Programming Language :: Python :: 3.11
Classifier: Programming Language :: Python :: 3.12
Requires-Dist: pyserial (>=3.5,<4.0)
Requires-Dist: tabulate (>=0.9.0,<0.10.0)
Requires-Dist: typer (>=0.6.1,<0.7.0)
Project-URL: Repository, https://gitlab.com/aiba.kg93/puloon-py
